rasvec/__init__.py
rasvec/download/__init__.py
rasvec/download/tms_to_geotiff.py
rasvec/ml/__init__.py
rasvec/ml/train_test_split.py
rasvec/raster/__init__.py
rasvec/raster/patchify.py
rasvec/raster/vectorization.py
rasvec/vector/__init__.py
rasvec/vector/clip_vector_by_raster.py
rasvec/vector/create_grid_on_vector.py
rasvec/vector/rasterize.py
rasvec/view/__init__.py
rasvec/view/view.py
rasvec-0.1.5.dist-info/licenses/LICENSE
rasvec-0.1.5.dist-info/METADATA
rasvec-0.1.5.dist-info/WHEEL
rasvec-0.1.5.dist-info/top_level.txt
rasvec-0.1.5.dist-info/RECORD
