Metadata-Version: 2.4
Name: rasvec
Version: 0.1.5
Summary: A Geospatial data handling library.
Author-email: Nischal Singh <nischal.singh38@gmail.com>
License-Expression: MIT
Project-URL: Homepage, https://github.com/davnish/rasvec.git
Project-URL: Documentation, https://rasvec.readthedocs.io
Keywords: geospatial,geopython,raster,vector,machine-learning
Requires-Python: >=3.9
License-File: LICENSE
Requires-Dist: pillow
Requires-Dist: rasterio
Requires-Dist: patchify
Requires-Dist: geopandas
Requires-Dist: xyzservices
Requires-Dist: requests
Dynamic: license-file
